langchain_ollama/__init__.py
langchain_ollama/chat_models.py
langchain_ollama/embeddings.py
langchain_ollama/llms.py
langchain_ollama/py.typed
gigachain_ollama-0.1.1.dist-info/LICENSE
gigachain_ollama-0.1.1.dist-info/METADATA
gigachain_ollama-0.1.1.dist-info/WHEEL
gigachain_ollama-0.1.1.dist-info/RECORD
